authorizenet/__init__.py
authorizenet/apicontractsv1.py
authorizenet/apicontrollers.py
authorizenet/apicontrollersbase.py
authorizenet/constants.py
authorizenet/utility.py
authorizenet_n1-1.1.4.dist-info/LICENSE.txt
authorizenet_n1-1.1.4.dist-info/METADATA
authorizenet_n1-1.1.4.dist-info/WHEEL
authorizenet_n1-1.1.4.dist-info/top_level.txt
authorizenet_n1-1.1.4.dist-info/RECORD
